{
    "tip": "hikaye",
    "sayfalar": [
        "Hello (Merhaba), my (benim) name (adım) is (-dır) John (John).\n\nI (Ben) like (severim) to (mek/mak) read (okumayı) this (bu) book (kitap) every (her) night (gece).\n\nCan (-ebilmek) I (ben) have (almak) a (bir) glass (bardak) of (-ın/-in) water (su), please (lütfen)?\n\nThis (Bu) apple (elma) is (-dır) green (yeşil) and (ve) sweet (tatlı).\n\nMy (Benim) father (babam) drives (sürer) a (bir) white (beyaz) car (araba).\n\nOur (Bizim) house (evimiz) has (sahiptir/var) a (bir) beautiful (güzel) garden (bahçe).\n\nThe (bilinen) cat (kedi) is (-dır) playing (oynuyor) with (ile) a (bir) ball (top).\n\nMy (Benim) dog (köpeğim) runs (koşar) very (çok) fast (hızlı) in (içinde/-da) the (bilinen) park (park).\n\nShe (O - kadın) wears (giyer) a (bir) red (kırmızı) dress (elbise) to (-e/-a) the (bilinen) party (parti).\n\nThe (bilinen) sky (gökyüzü) is (-dır) very (çok) blue (mavi) today (bugün).\n\nThat (Şu) is (-dır) a (bir) very (çok) big (büyük) building (bina).\n\nI (Ben) have (sahibim/var) a (bir) small (küçük) phone (telefon) in (içinde) my (benim) pocket (cep).\n\nWe (Biz) eat (yeriz) breakfast (kahvaltı) at (-de/-da) 8 (sekiz) o'clock (saat).\n\nI (Ben) drink (içerim) milk (süt) before (önce) I (ben) sleep (uyurum).\n\nI (Ben) usually (genellikle) sleep (uyurum) for (boyunca/için) eight (sekiz) hours (saat).\n\nWe (Biz) go (gideriz) to (-e/-a) the (bilinen) cinema (sinema) on (-de/-da) Fridays (Cumaları).\n\nPlease (Lütfen) come (gel) to (-e/-a) my (benim) birthday (doğum günü) party (parti).\n\nMy (Benim) mother (annem) makes (yapar) the (en) best (iyi) cake (kek).\n\nMy (Benim) father (babam) is (-dır) a (bir) tall (uzun) man (adam).\n\nAli (Ali) is (-dır) my (benim) best (en iyi) friend (arkadaşım) at (-de/-da) school (okul)."
    ],
    "sozluk": {
        "of": "ile ilgili",
        "beautiful": "Güzel",
        "she": "o",
        "cep": "cep",
        "saat": "an",
        "bina": "bina",
        "biz": "biz",
        "breakfast": "kahvaltı",
        "party": "parti",
        "var": "bizim",
        "wears": "giyer",
        "bir": "bir",
        "we": "Biz",
        "for": "için",
        "tall": "uzun",
        "birthday": "doğum günü",
        "mak": "mak",
        "with": "ile",
        "gel": "jel",
        "the": "the",
        "adım": "adım",
        "bugün": "bugün",
        "doğum": "doğum",
        "araba": "araba",
        "very": "çok",
        "gideriz": "gideriz",
        "dress": "elbise",
        "like": "beğenmek",
        "bardak": "bardak",
        "ali": "Ali",
        "garden": "bahçe",
        "please": "Lütfen",
        "elbise": "elbise",
        "okumayı": "okumayı",
        "uyurum": "uyurum",
        "this": "Bu",
        "sekiz": "sekiz",
        "benim": "benim",
        "fridays": "cuma günleri",
        "tatlı": "tatlı",
        "okul": "okul",
        "çok": "çok",
        "giyer": "giyer",
        "every": "Her",
        "is": "öyle",
        "elma": "elma",
        "kedi": "kedi",
        "önce": "önce",
        "cumaları": "cumaları",
        "runs": "koşar",
        "da": "Ve",
        "sky": "gökyüzü",
        "kek": "kek",
        "mavi": "mavi",
        "severim": "severim",
        "in": "içinde",
        "fast": "hızlı",
        "içerim": "içerim",
        "my": "Benim",
        "man": "Adam",
        "makes": "yapar",
        "name": "isim",
        "ball": "top",
        "ben": "ben",
        "mek": "mek",
        "cake": "kek",
        "uzun": "uzun",
        "have": "sahip olmak",
        "ile": "ile",
        "today": "Bugün",
        "playing": "oynuyor",
        "boyunca": "boyunca",
        "telefon": "telefon",
        "clock": "saat",
        "kırmızı": "kırmızı",
        "cinema": "sinema",
        "koşar": "koşar",
        "on": "Açık",
        "milk": "süt",
        "su": "öyle",
        "sweet": "tatlı",
        "drives": "sürücüler",
        "bizim": "bizim",
        "annem": "annem",
        "en": "içinde",
        "hızlı": "hızlı",
        "küçük": "küçük",
        "best": "en iyi",
        "büyük": "büyük",
        "pocket": "cep",
        "sahibim": "sahibim",
        "night": "gece",
        "sinema": "sinema",
        "bilinen": "bilinen",
        "usually": "genellikle",
        "genellikle": "genellikle",
        "içinde": "içinde",
        "green": "yeşil",
        "ebilmek": "ebilmek",
        "sürer": "sürer",
        "building": "bina",
        "köpeğim": "köpeğim",
        "at": "en",
        "eight": "sekiz",
        "dır": "dır",
        "her": "o",
        "read": "Okumak",
        "kitap": "kitap",
        "merhaba": "merhaba",
        "bahçe": "bahçe",
        "before": "önce",
        "phone": "telefon",
        "bu": "Bu",
        "kadın": "kadın",
        "to": "ile",
        "white": "beyaz",
        "that": "O",
        "ın": "ın",
        "beyaz": "beyaz",
        "evimiz": "evimiz",
        "iyi": "iyi",
        "has": "sahip olmak",
        "glass": "bardak",
        "gece": "gece",
        "top": "tepe",
        "güzel": "güzel",
        "can": "olabilmek",
        "babam": "babam",
        "kahvaltı": "kahvaltı",
        "adam": "Adem",
        "günü": "günü",
        "de": "ile ilgili",
        "and": "Ve",
        "hours": "saat",
        "yeşil": "yeşil",
        "ve": "ve",
        "sahiptir": "sahiptir",
        "almak": "almak",
        "için": "için",
        "yapar": "yapar",
        "lütfen": "lütfen",
        "şu": "şu",
        "school": "okul",
        "oynuyor": "oynuyor",
        "parti": "parti",
        "yeriz": "yeriz",
        "süt": "süt",
        "gökyüzü": "gökyüzü",
        "park": "park",
        "our": "bizim",
        "john": "John",
        "arkadaşım": "arkadaşım"
    }
}