{
    "tip": "hikaye",
    "sayfalar": [
        "I (Ben) go (giderim) to (-e/-a) school (okul) every (her) day (gün).\n\nMy (Benim) teacher (öğretmenim) is (-dır) very (çok) kind (kibar).\n\nHe (O) is (-dır) a (bir) good (iyi) student (öğrenci).\n\nThe (Bilinen) children (çocuklar) are (-dır) very (çok) happy (mutlu).\n\nPlease (Lütfen) do (yapma) not (değil) be (ol) sad (üzgün).\n\nThe (Bilinen) sun (güneş) is (-dır) very (çok) hot (sıcak).\n\nLook (Bak) at (-e/-a) the (bilinen) moon (ay) at (-de/-da) night (gece).\n\nI (Ben) love (severim) my (benim) family (ailem).\n\nWe (Biz) run (koşarız) in (-de/-da) the (bilinen) park (park).\n\nThey (Onlar) walk (yürürler) to (-e/-a) their (onların) home (ev).\n\nThe (Bilinen) book (kitap) is (-dır) on (üzerinde) the (bilinen) table (masa).\n\nPlease (Lütfen) sit (otur) on (üzerine) this (bu) chair (sandalye).\n\nI (Ben) write (yazarım) with (ile) a (bir) blue (mavi) pen (tükenmez kalem).\n\nShe (O) has (sahiptir/var) a (bir) yellow (sarı) pencil (kurşun kalem).\n\nMy (Benim) bag (çantam) is (-dır) very (çok) heavy (ağır).\n\nOpen (Aç) the (bilinen) door (kapı), please (lütfen).\n\nI (Ben) look (bakarım) out (dışarı) the (bilinen) window (pencere).\n\nThis (Bu) room (oda) is (-dır) very (çok) clean (temiz).\n\nI (Ben) sleep (uyurum) in (-de/-da) my (benim) bed (yatak).\n\nWe (Biz) play (oynarız) games (oyunlar) on (üzerinde) the (bilinen) computer (bilgisayar)."
    ],
    "sozluk": {
        "ay": "öyle",
        "üzerinde": "üzerinde",
        "she": "o",
        "çantam": "çantam",
        "sit": "oturmak",
        "biz": "biz",
        "otur": "kötü şans",
        "var": "bizim",
        "oyunlar": "oyunlar",
        "tükenmez": "tükenmez",
        "bir": "bir",
        "children": "çocuklar",
        "we": "Biz",
        "mutlu": "mutlu",
        "with": "ile",
        "the": "the",
        "they": "Onlar",
        "write": "yazmak",
        "their": "onların",
        "üzgün": "üzgün",
        "öğretmenim": "öğretmenim",
        "be": "olmak",
        "onlar": "bunlar",
        "not": "Olumsuz",
        "güneş": "güneş",
        "very": "çok",
        "day": "gün",
        "good": "iyi",
        "bak": "fırında pişirmek",
        "please": "Lütfen",
        "oda": "oda",
        "uyurum": "uyurum",
        "this": "Bu",
        "hot": "sıcak",
        "benim": "benim",
        "okul": "okul",
        "çok": "çok",
        "oynarız": "oynarız",
        "every": "Her",
        "he": "O",
        "yellow": "sarı",
        "is": "öyle",
        "sarı": "sarı",
        "aç": "aç",
        "ol": "ol",
        "heavy": "ağır",
        "da": "Ve",
        "giderim": "giderim",
        "mavi": "mavi",
        "severim": "severim",
        "ev": "ev",
        "in": "içinde",
        "gün": "gün",
        "yatak": "yatak",
        "clean": "temiz",
        "my": "Benim",
        "dışarı": "dışarı",
        "home": "Ev",
        "ağır": "ağır",
        "games": "oyunlar",
        "ben": "ben",
        "ile": "ile",
        "kurşun": "kurşun",
        "yürürler": "yürürler",
        "out": "dışarı",
        "üzerine": "üzerine",
        "on": "Açık",
        "yapma": "yapma",
        "ailem": "ailem",
        "kalem": "kalem",
        "yazarım": "yazarım",
        "kind": "tür",
        "değil": "değil",
        "night": "gece",
        "family": "aile",
        "onların": "onların",
        "are": "öyle",
        "bilinen": "bilinen",
        "çocuklar": "çocuklar",
        "do": "Yapmak",
        "sandalye": "sandalye",
        "at": "en",
        "open": "açık",
        "dır": "dır",
        "her": "o",
        "temiz": "temiz",
        "look": "Bakmak",
        "kitap": "kitap",
        "öğrenci": "öğrenci",
        "bu": "Bu",
        "masa": "zaman",
        "to": "ile",
        "iyi": "iyi",
        "has": "sahip olmak",
        "kibar": "kibar",
        "gece": "gece",
        "koşarız": "koşarız",
        "bilgisayar": "bilgisayar",
        "bakarım": "bakarım",
        "de": "ile ilgili",
        "kapı": "kapı",
        "sahiptir": "sahiptir",
        "lütfen": "lütfen",
        "pencere": "pencere",
        "play": "oynamak",
        "sıcak": "sıcak",
        "park": "park"
    }
}