{
    "tip": "hikaye",
    "sayfalar": [
        "That (Şu) man (adam) is (-dır) my (benim) father (babam).\n\nThe (Bilinen) woman (kadın) is (-dır) very (çok) beautiful (güzel).\n\nThe (Bilinen) child (çocuk) is (-dır) playing (oynuyor) in (-de/-da) the (bilinen) garden (bahçe).\n\nThe (Bilinen) boy (erkek çocuk) has (sahiptir/var) a (bir) blue (mavi) ball (top).\n\nThe (Bilinen) girl (kız çocuk) likes (sever) her (onun) doll (oyuncak bebek).\n\nMy (Benim) family (ailem) lives (yaşar) in (-de/-da) a (bir) big (büyük) house (ev).\n\nMany (Birçok) people (insanlar) are (-dır) in (-de/-da) the (bilinen) park (park).\n\nHave (Sahip ol/İyi geçsin) a (bir) nice (güzel) day (gün).\n\nWe (Biz) sleep (uyuruz) at (-de/-da) night (gece).\n\nI (Ben) drink (içerim) coffee (kahve) in (-de/-da) the (bilinen) morning (sabah).\n\nWe (Biz) eat (yeriz) dinner (akşam yemeği) in (-de/-da) the (bilinen) evening (akşam).\n\nToday (Bugün) is (-dır) a (bir) happy (mutlu) day (gün).\n\nI (Ben) go (giderim) to (-e/-a) school (okul) tomorrow (yarın).\n\nYesterday (Dün) was (idi) very (çok) cold (soğuk).\n\nWhat (Ne) is (-dır) the (bilinen) time (zaman/saat)?\n\nOne (Bir) year (yıl) has (sahiptir/var) twelve (on iki) months (aylar).\n\nOne (Bir) week (hafta) has (sahiptir/var) seven (yedi) days (günler).\n\nJanuary (Ocak) is (-dır) the (bilinen) first (ilk) month (ay)."
    ],
    "sozluk": {
        "beautiful": "Güzel",
        "was": "öyleydi",
        "sabah": "sabah",
        "ay": "öyle",
        "saat": "an",
        "days": "günler",
        "ilk": "ilk",
        "bebek": "bebek",
        "biz": "biz",
        "yedi": "yedi",
        "sahip": "sahip",
        "var": "bizim",
        "bir": "bir",
        "we": "Biz",
        "idi": "öyleydi",
        "mutlu": "mutlu",
        "the": "the",
        "bugün": "bugün",
        "very": "çok",
        "twelve": "on iki",
        "kahve": "kahve",
        "january": "Ocak",
        "garden": "bahçe",
        "çocuk": "çocuk",
        "benim": "benim",
        "okul": "okul",
        "çok": "çok",
        "is": "öyle",
        "iki": "değin",
        "soğuk": "soğuk",
        "ol": "ol",
        "da": "Ve",
        "ne": "öyle",
        "akşam": "akşam",
        "months": "aylar",
        "giderim": "giderim",
        "aylar": "aylar",
        "mavi": "mavi",
        "many": "birçok",
        "hafta": "hafta",
        "ev": "ev",
        "in": "içinde",
        "gün": "gün",
        "içerim": "içerim",
        "my": "Benim",
        "insanlar": "insanlar",
        "ball": "top",
        "ben": "ben",
        "have": "sahip olmak",
        "playing": "oynuyor",
        "on": "Açık",
        "dinner": "akşam yemeği",
        "ailem": "ailem",
        "büyük": "büyük",
        "are": "öyle",
        "bilinen": "bilinen",
        "one": "bir",
        "nice": "Güzel",
        "ocak": "ocak",
        "at": "en",
        "dır": "dır",
        "her": "o",
        "günler": "günler",
        "bahçe": "bahçe",
        "erkek": "erkek",
        "yaşar": "yaşar",
        "kadın": "kadın",
        "yemeği": "yemeği",
        "to": "ile",
        "that": "O",
        "likes": "beğeniler",
        "yarın": "yarın",
        "has": "sahip olmak",
        "doll": "oyuncak bebek",
        "top": "tepe",
        "gece": "gece",
        "yıl": "yıl",
        "güzel": "güzel",
        "babam": "babam",
        "what": "Ne",
        "first": "Birinci",
        "adam": "Adem",
        "seven": "Yedi",
        "de": "ile ilgili",
        "sever": "koparmak",
        "dün": "dün",
        "oyuncak": "oyuncak",
        "yi": "Yapmak",
        "sahiptir": "sahiptir",
        "şu": "şu",
        "oynuyor": "oynuyor",
        "yeriz": "yeriz",
        "onun": "onun",
        "zaman": "zaman",
        "birçok": "birçok",
        "uyuruz": "uyuruz",
        "kız": "kız",
        "lives": "yaşıyor",
        "geçsin": "geçsin"
    }
}