{
    "tip": "hikaye",
    "sayfalar": [
        "I (Ben) love (severim) good (iyi) food (yiyecek).\n\nThis (Bu) bread (ekmek) is (-dır) very (çok) fresh (taze).\n\nI (Ben) drink (içerim) a (bir) glass (bardak) of (-ın/-in) milk (süt) every (her) day (gün).\n\nWe (Biz) drink (içeriz) hot (sıcak) tea (çay) in (-de/-da) the (bilinen) morning (sabah).\n\nMy (Benim) mother (annem) loves (sever) Turkish (Türk) coffee (kahve).\n\nWe (Biz) eat (yeriz) rice (pirinç) for (için) dinner (akşam yemeği).\n\nI (Ben) do (yapmak) not (değil/me-ma) eat (yemek) meat (et).\n\nThe (Bilinen) cat (kedi) likes (sever) to (-mek/-mak) eat (yemek) fish (balık).\n\nPlease (Lütfen) give (ver) me (bana) an (bir) egg (yumurta).\n\nDo (Yapmak) you (sen) want (istemek) sugar (şeker) in (içinde) your (senin) tea (çay)?\n\nPlease (Lütfen) pass (uzat) the (bilinen) salt (tuz).\n\nThis (Bu) cake (kek) is (-dır) very (çok) sweet (tatlı).\n\nThe (Bilinen) soup (çorba) is (-dır) very (çok) hot (sıcak).\n\nI (Ben) want (isterim) cold (soğuk) water (su), please (lütfen)."
    ],
    "sozluk": {
        "of": "ile ilgili",
        "sabah": "sabah",
        "you": "Sen",
        "yumurta": "yumurta",
        "sen": "sen",
        "senin": "Pazartesi",
        "biz": "biz",
        "çorba": "çorba",
        "loves": "seviyor",
        "ekmek": "ekmek",
        "et": "ve",
        "bir": "bir",
        "we": "Biz",
        "for": "için",
        "türk": "türk",
        "mak": "mak",
        "the": "the",
        "yiyecek": "yiyecek",
        "pirinç": "pirinç",
        "not": "Olumsuz",
        "very": "çok",
        "kahve": "kahve",
        "bardak": "bardak",
        "içeriz": "içeriz",
        "please": "Lütfen",
        "this": "Bu",
        "tuz": "tuz",
        "benim": "benim",
        "tatlı": "tatlı",
        "pass": "geçmek",
        "an": "BİR",
        "çok": "çok",
        "every": "Her",
        "is": "öyle",
        "kedi": "kedi",
        "soğuk": "soğuk",
        "da": "Ve",
        "akşam": "akşam",
        "kek": "kek",
        "severim": "severim",
        "in": "içinde",
        "gün": "gün",
        "içerim": "içerim",
        "my": "Benim",
        "ben": "ben",
        "yapmak": "yapmak",
        "mek": "mek",
        "cake": "kek",
        "şeker": "şeker",
        "ma": "anne",
        "dinner": "akşam yemeği",
        "annem": "annem",
        "su": "öyle",
        "me": "Ben",
        "değil": "değil",
        "yemek": "yemek",
        "balık": "balık",
        "bilinen": "bilinen",
        "istemek": "istemek",
        "soup": "çorba",
        "bana": "bana",
        "içinde": "içinde",
        "do": "Yapmak",
        "dır": "dır",
        "her": "o",
        "bu": "Bu",
        "ver": "ver",
        "turkish": "Türkçe",
        "yemeği": "yemeği",
        "fresh": "taze",
        "to": "ile",
        "likes": "beğeniler",
        "ın": "ın",
        "uzat": "Harcanan",
        "iyi": "iyi",
        "want": "istek",
        "glass": "bardak",
        "taze": "taze",
        "de": "ile ilgili",
        "sever": "koparmak",
        "için": "için",
        "isterim": "isterim",
        "lütfen": "lütfen",
        "your": "senin",
        "yeriz": "yeriz",
        "sıcak": "sıcak",
        "süt": "süt",
        "çay": "çay"
    }
}