{
    "tip": "hikaye",
    "sayfalar": [
        "You (Sen) are (-sın) a (bir) very (çok) good (iyi) friend (arkadaş).\n\nThe (Bilinen) weather (hava) is (-dır) very (çok) bad (kötü) today (bugün).\n\nThis (Bu) question (soru) is (-dır) very (çok) easy (kolay).\n\nThe (Bilinen) exam (sınav) is (-dır) very (çok) hard (zor).\n\nMy (Benim) car (arabam) is (-dır) very (çok) fast (hızlı).\n\nThe (Bilinen) bus (otobüs) is (-dır) very (çok) slow (yavaş).\n\nI (Ben) have (sahibim/var) a (bir) new (yeni) phone (telefon).\n\nMy (Benim) computer (bilgisayarım) is (-dır) old (eski).\n\nMy (Benim) room (odam) is (-dır) very (çok) clean (temiz).\n\nYour (Senin) shoes (ayakkabıların) are (-dır) dirty (kirli)."
    ],
    "sozluk": {
        "hava": "hava durumu",
        "this": "Bu",
        "arkadaş": "arkadaş",
        "weather": "hava durumu",
        "iyi": "iyi",
        "you": "Sen",
        "benim": "benim",
        "hızlı": "hızlı",
        "arabam": "arabam",
        "eski": "eski",
        "sen": "sen",
        "senin": "Pazartesi",
        "çok": "çok",
        "kötü": "kötü",
        "sahibim": "sahibim",
        "is": "öyle",
        "sınav": "sınav",
        "var": "bizim",
        "are": "öyle",
        "yeni": "yeni",
        "bilinen": "bilinen",
        "bir": "bir",
        "zor": "zor",
        "sın": "sın",
        "the": "the",
        "odam": "Adam",
        "exam": "sınav",
        "temiz": "temiz",
        "kirli": "kirli",
        "dır": "dır",
        "bugün": "bugün",
        "your": "senin",
        "otobüs": "otobüs",
        "my": "Benim",
        "shoes": "ayakkabı",
        "bus": "otobüs",
        "very": "çok",
        "question": "soru",
        "bilgisayarım": "bilgisayarım",
        "ben": "ben",
        "ayakkabıların": "ayakkabıların",
        "soru": "soru",
        "bu": "Bu",
        "phone": "telefon",
        "kolay": "kolay",
        "yavaş": "yavaş",
        "have": "sahip olmak",
        "telefon": "telefon"
    }
}