{
    "tip": "hikaye",
    "sayfalar": [
        "Please (Lütfen) open (aç) the (bilinen) door (kapı).\n\nI (Ben) close (kapatırım) the (bilinen) window (pencere) at (-de/-da) night (gece).\n\nI (Ben) see (görürüm) a (bir) green (yeşil) tree (ağaç).\n\nLook (Bak) at (-e/-a) the (bilinen) board (tahta), please (lütfen).\n\nCan (-ebilir misin) you (sen) hear (duymak) me (beni)?\n\nListen (Dinle) to (-i) the (bilinen) teacher (öğretmen).\n\nI (Ben) speak (konuşurum) English (İngilizce) and (ve) Turkish (Türkçe).\n\nPlease (Lütfen) say (söyle) hello (merhaba) to (-e/-a) your (senin) father (babana).\n\nCan (-ebilir miyim) I (ben) ask (sormak) a (bir) question (soru)?\n\nPlease (Lütfen) answer (cevap ver) the (bilinen) phone (telefon)."
    ],
    "sozluk": {
        "beni": "beni",
        "bak": "fırında pişirmek",
        "söyle": "söyle",
        "ngilizce": "ngilizce",
        "you": "Sen",
        "ağaç": "ağaç",
        "ebilir": "olabilmek",
        "english": "İngilizce",
        "babana": "birlikte yaşıyorlar",
        "gece": "gece",
        "sen": "sen",
        "miyim": "miyim",
        "senin": "Pazartesi",
        "can": "olabilmek",
        "cevap": "cevap",
        "me": "Ben",
        "tahta": "tahta",
        "telefon": "telefon",
        "aç": "aç",
        "bilinen": "bilinen",
        "bir": "bir",
        "öğretmen": "öğretmen",
        "da": "Ve",
        "de": "ile ilgili",
        "green": "yeşil",
        "and": "Ve",
        "kapı": "kapı",
        "yeşil": "yeşil",
        "the": "the",
        "ve": "ve",
        "at": "en",
        "dinle": "dinle",
        "lütfen": "lütfen",
        "konuşurum": "konuşurum",
        "pencere": "pencere",
        "görürüm": "görürüm",
        "merhaba": "merhaba",
        "your": "senin",
        "türkçe": "türkçe",
        "question": "soru",
        "duymak": "duymak",
        "misin": "misin",
        "ben": "ben",
        "board": "pano",
        "sormak": "sormak",
        "soru": "soru",
        "phone": "telefon",
        "ver": "ver",
        "tree": "ağaç",
        "turkish": "Türkçe",
        "please": "Lütfen",
        "to": "ile",
        "kapatırım": "kapatırım"
    }
}