{
    "tip": "hikaye",
    "sayfalar": [
        "I (Ben) buy (satın alırım) bread (ekmek) every (her) day (gün).\n\nMy (Benim) father (babam) sells (satar) his (onun) old (eski) car (arabasını).\n\nPlease (Lütfen) pay (öde) the (bilinen) money (parayı) now (şimdi).\n\nCan (-ebilir miyim) I (ben) use (kullanmak) your (senin) pen (kalemini)?\n\nMy (Benim) mother (annem) makes (yapar) very (çok) good (iyi) cake (kek).\n\nPlease (Lütfen) give (ver) me (bana) that (şu) book (kitabı).\n\nI (Ben) take (alırım/binerim) the (bilinen) bus (otobüs) to (-e/-a) school (okul).\n\nWe (Biz) find (buluruz) a (bir) ball (top) in (-de/-da) the (bilinen) garden (bahçe).\n\nDo (Yapma) not (değil/me-ma) lose (kaybetme) your (senin) keys (anahtarlarını).\n\nCan (-ebilir misin) you (sen) help (yardım etmek) me (bana), please (lütfen)?"
    ],
    "sozluk": {
        "you": "Sen",
        "sen": "sen",
        "senin": "Pazartesi",
        "biz": "biz",
        "şimdi": "şimdi",
        "his": "onun",
        "ekmek": "ekmek",
        "bir": "bir",
        "we": "Biz",
        "the": "the",
        "satın": "satın",
        "keys": "anahtarlar",
        "not": "Olumsuz",
        "very": "çok",
        "parayı": "parayı",
        "please": "Lütfen",
        "garden": "bahçe",
        "benim": "benim",
        "sells": "satıyor",
        "money": "para",
        "çok": "çok",
        "okul": "okul",
        "kaybetme": "kaybetme",
        "etmek": "etmek",
        "every": "Her",
        "kullanmak": "kullanmak",
        "da": "Ve",
        "kek": "kek",
        "in": "içinde",
        "gün": "gün",
        "my": "Benim",
        "makes": "yapar",
        "bus": "otobüs",
        "ball": "top",
        "ben": "ben",
        "binerim": "görelim",
        "cake": "kek",
        "ma": "anne",
        "yapma": "yapma",
        "annem": "annem",
        "yardım": "yardım",
        "eski": "eski",
        "miyim": "miyim",
        "me": "Ben",
        "değil": "değil",
        "satar": "hırsızlık yapmak",
        "bilinen": "bilinen",
        "bana": "bana",
        "do": "Yapmak",
        "alırım": "alırım",
        "her": "o",
        "otobüs": "otobüs",
        "bahçe": "bahçe",
        "ver": "ver",
        "kalemini": "kalemini",
        "to": "ile",
        "arabasını": "arabasını",
        "that": "O",
        "iyi": "iyi",
        "ebilir": "olabilmek",
        "top": "tepe",
        "babam": "babam",
        "can": "olabilmek",
        "buluruz": "buluruz",
        "öde": "Kader",
        "now": "Şimdi",
        "de": "ile ilgili",
        "yapar": "yapar",
        "anahtarlarını": "anahtarlarını",
        "kitabı": "kitabı",
        "lütfen": "lütfen",
        "şu": "şu",
        "your": "senin",
        "onun": "onun",
        "misin": "misin"
    }
}