{
    "tip": "hikaye",
    "sayfalar": [
        "My (Benim) house (evim) is (-dır) on (-de/-da) this (bu) street (sokak).\n\nIstanbul (İstanbul) is (-dır) a (bir) very (çok) big (büyük) city (şehir).\n\nI (Ben) love (severim) my (benim) country (ülke/ülkemi).\n\nThis (Bu) shop (mağaza) is (-dır) open (açık) every (her) day (gün).\n\nWe (Biz) buy (satın alırız) food (yiyecek) from (-den/-dan) the (bilinen) market (market).\n\nThe (Bilinen) doctor (doktor) is (-dır) in (-de/-da) the (bilinen) hospital (hastane).\n\nThe (Bilinen) police (polis) has (sahiptir/var) a (bir) fast (hızlı) car (araba).\n\nMy (Benim) father (babam) works (çalışır) in (-de/-da) a (bir) bank (banka).\n\nThe (Bilinen) children (çocuklar) run (koşarlar) in (-de/-da) the (bilinen) park (park)."
    ],
    "sozluk": {
        "this": "Bu",
        "on": "Açık",
        "ülke": "ülke",
        "şehir": "şehir",
        "benim": "benim",
        "has": "sahip olmak",
        "hızlı": "hızlı",
        "mağaza": "mağaza",
        "büyük": "büyük",
        "biz": "biz",
        "çok": "çok",
        "from": "itibaren",
        "stanbul": "stanbul",
        "babam": "babam",
        "istanbul": "İstanbul",
        "every": "Her",
        "is": "öyle",
        "çalışır": "çalışıyor",
        "var": "bizim",
        "bilinen": "bilinen",
        "çocuklar": "çocuklar",
        "bir": "bir",
        "dan": "Ve",
        "children": "çocuklar",
        "da": "Ve",
        "de": "ile ilgili",
        "we": "Biz",
        "banka": "banka",
        "the": "the",
        "ülkemi": "ülkemi",
        "severim": "severim",
        "satın": "satın",
        "yiyecek": "yiyecek",
        "doctor": "doktor",
        "dır": "dır",
        "evim": "evim",
        "her": "o",
        "in": "içinde",
        "gün": "gün",
        "koşarlar": "koşarlar",
        "araba": "araba",
        "my": "Benim",
        "very": "çok",
        "polis": "polis",
        "sahiptir": "sahiptir",
        "works": "çalışır",
        "ben": "ben",
        "bu": "Bu",
        "açık": "açık",
        "sokak": "sokak",
        "alırız": "alırız",
        "doktor": "doktor",
        "hastane": "hastane",
        "den": "BT"
    }
}