{
    "tip": "hikaye",
    "sayfalar": [
        "I (Ben) wash (yıkarım) my (benim) hands (ellerimi) every (her) day (gün).\n\nMy (Benim) head (kafam) is (-dır) very (çok) hot (sıcak).\n\nI (Ben) see (görürüm) with (ile) my (benim) eyes (gözlerim).\n\nThe (Bilinen) rabbit (tavşan) has (sahiptir/var) two (iki) long (uzun) ears (kulaklar).\n\nMy (Benim) nose (burnum) is (-dır) very (çok) cold (soğuk).\n\nPlease (Lütfen) open (aç) your (senin) mouth (ağzını).\n\nShe (O) has (sahiptir/var) a (bir) very (çok) beautiful (güzel) face (yüz).\n\nMy (Benim) mother (annem) has (sahiptir/var) black (siyah) hair (saç).\n\nThe (Bilinen) chair (sandalye) has (sahiptir/var) four (dört) legs (bacaklar/ayaklar)."
    ],
    "sozluk": {
        "saç": "saç",
        "rabbit": "tavşan",
        "beautiful": "Güzel",
        "she": "o",
        "annem": "annem",
        "benim": "benim",
        "has": "sahip olmak",
        "long": "uzun",
        "ellerimi": "ellerimi",
        "hands": "eller",
        "güzel": "güzel",
        "senin": "Pazartesi",
        "ayaklar": "ayaklar",
        "çok": "çok",
        "two": "iki",
        "black": "siyah",
        "ağzını": "ağzını",
        "every": "Her",
        "is": "öyle",
        "iki": "değin",
        "var": "bizim",
        "kulaklar": "kulaklar",
        "burnum": "burnum",
        "dört": "dört",
        "eyes": "gözler",
        "aç": "aç",
        "bilinen": "bilinen",
        "soğuk": "soğuk",
        "siyah": "siyah",
        "bir": "bir",
        "yüz": "yüz",
        "yıkarım": "yıkarım",
        "kafam": "kafam",
        "with": "ile",
        "the": "the",
        "sahiptir": "sahiptir",
        "sandalye": "sandalye",
        "four": "dört",
        "dır": "dır",
        "her": "o",
        "gözlerim": "gözlerim",
        "gün": "gün",
        "lütfen": "lütfen",
        "your": "senin",
        "görürüm": "görürüm",
        "tavşan": "tavşan",
        "my": "Benim",
        "very": "çok",
        "sıcak": "sıcak",
        "bacaklar": "bacaklar",
        "ben": "ben",
        "wash": "yıkamak",
        "legs": "bacaklar",
        "uzun": "uzun",
        "ile": "ile",
        "please": "Lütfen",
        "ears": "kulaklar"
    }
}